[
  {
    "text": "Vaisala Thunderstorm",
    "img": "/assets/home/vaisala",
    "link": "https://storm.vaisala.com/thunderstorm/login",
    "isBig": false
  },
  {
    "text": "Ramsdis Infrarrojo Loop",
    "img": "/assets/home/infrarrojo",
    "link": "http://rammb.cira.colostate.edu/ramsdis/online/loop.asp?data_folder=rmtc/rmtcnhir48&width=640&height=480",
    "isBig": false
  },
  {
    "text": "Sondeos Wyoming",
    "img": "/assets/home/sondeo",
    "link": "http://weather.uwyo.edu/upperair/sounding.html",
    "isBig": false
  },
  {
    "text": "Mapa de lluvia nacional",
    "img": "/assets/home/mapa_lluvia",
    "link": "http://intra-files.imn.ac.cr/estaciones/esta.html",
    "isBig": false
  },
  {
    "text": "Valle Central (este)",
    "img": "/assets/home/VC_este",
    "link": "https://www.imn.ac.cr/especial/gam2.html",
    "isBig": false
  },
  {
    "text": "Valle Central (oeste)",
    "img": "/assets/home/VC_oeste",
    "link": "https://www.imn.ac.cr/especial/gam.html",
    "isBig": false
  },
  {
    "text": "ECMWF Model",
    "img": "/assets/home/nmme-apcpna",
    "link": "https://www.tropicaltidbits.com/analysis/models/?model=ecmwf&region=watl&pkg=uv850_vort&runtime=2017090512&fh=168&xpos=0&ypos=0",
    "isBig": false
  }
]
